cfgpie/__init__.py
cfgpie/constants.py
cfgpie/exceptions.py
cfgpie/handlers.py
cfgpie/utils.py
cfgpie-3.0.3.dist-info/LICENSE
cfgpie-3.0.3.dist-info/METADATA
cfgpie-3.0.3.dist-info/WHEEL
cfgpie-3.0.3.dist-info/top_level.txt
cfgpie-3.0.3.dist-info/RECORD
